YuanmengXiangmuBijiWangzhuanJuejinShicaoXiangmuDianzishu20191230Fix1/README.md
YuanmengXiangmuBijiWangzhuanJuejinShicaoXiangmuDianzishu20191230Fix1/__init__.py
YuanmengXiangmuBijiWangzhuanJuejinShicaoXiangmuDianzishu20191230Fix1/__main__.py
YuanmengXiangmuBijiWangzhuanJuejinShicaoXiangmuDianzishu20191230Fix1/file.pdf
YuanmengXiangmuBijiWangzhuanJuejinShicaoXiangmuDianzishu20191230Fix1/index.html
yuanmeng_xiangmu_biji_wangzhuan_juejin_shicao_xiangmu_dianzishu_20191230_fix1-2025.3.25.0.dist-info/METADATA
yuanmeng_xiangmu_biji_wangzhuan_juejin_shicao_xiangmu_dianzishu_20191230_fix1-2025.3.25.0.dist-info/WHEEL
yuanmeng_xiangmu_biji_wangzhuan_juejin_shicao_xiangmu_dianzishu_20191230_fix1-2025.3.25.0.dist-info/entry_points.txt
yuanmeng_xiangmu_biji_wangzhuan_juejin_shicao_xiangmu_dianzishu_20191230_fix1-2025.3.25.0.dist-info/top_level.txt
yuanmeng_xiangmu_biji_wangzhuan_juejin_shicao_xiangmu_dianzishu_20191230_fix1-2025.3.25.0.dist-info/RECORD
